README.txt
setup.py
dtld/__init__.py
dtld/dtld.py
dtld/protocol.py
dtld/startfunc.py
dtld/top_domain.py
dtld1.0.egg-info/PKG-INFO
dtld1.0.egg-info/SOURCES.txt
dtld1.0.egg-info/dependency_links.txt
dtld1.0.egg-info/top_level.txt