Metadata-Version: 1.0
Name: dtld1.0
Version: 1.0
Summary: Custom Top level domain extractor 
Home-page: https://github.com/daviddexter/DTLD
Author: David Dexter www.blackspace.co.ke
Author-email: dmwangimail@gmail.com
License: GPL v3 or any later version
Keywords: top level domain,domain extractor
Platform: UNKNOWN
